alu_16bit.v
module alu_16bit (
    input  [15:0] a,
    input  [15:0] b,
    input  [3:0]  alu_control,
    output [15:0] result,
    output        zero,
    output        overflow
);

    reg [15:0] alu_result;
    reg        alu_overflow;

    always @(*) begin
        alu_overflow = 1'b0;
        case (alu_control)
            4'b0000: begin // ADD
                {alu_overflow, alu_result} = {1'b0, a} + {1'b0, b};
                alu_overflow = (a[15] == b[15]) && (alu_result[15] != a[15]);
            end
            4'b0001: begin // SUB
                {alu_overflow, alu_result} = {1'b0, a} - {1'b0, b};
                alu_overflow = (a[15] != b[15]) && (alu_result[15] != a[15]);
            end
            4'b0010: begin // AND
                alu_result = a & b;
            end
            4'b0011: begin // OR
                alu_result = a | b;
            end
            4'b0100: begin // XOR
                alu_result = a ^ b;
            end
            4'b0101: begin // SLT (Set Less Than)
                alu_result = ($signed(a) < $signed(b)) ? 16'h0001 : 16'h0000;
            end
            default: begin
                alu_result = 16'h0000;
            end
        endcase
    end

    assign result = alu_result;
    assign zero = (alu_result == 16'h0000);
    assign overflow = alu_overflow;

endmodule

alu_16bit_tb.v
module alu_16bit_tb;

    reg  [15:0] a;
    reg  [15:0] b;
    reg  [3:0]  alu_control;
    wire [15:0] result;
    wire        zero;
    wire        overflow;

    integer test_count;
    integer pass_count;
    integer fail_count;

    alu_16bit dut (
        .a(a),
        .b(b),
        .alu_control(alu_control),
        .result(result),
        .zero(zero),
        .overflow(overflow)
    );

    task check_result;
        input [15:0] expected_result;
        input        expected_zero;
        input        expected_overflow;
        input [255:0] test_name;
        begin
            test_count = test_count + 1;
            if (result == expected_result && zero == expected_zero && overflow == expected_overflow) begin
                $display("PASS: %s - A=%h, B=%h, Control=%b, Result=%h, Zero=%b, Overflow=%b", 
                         test_name, a, b, alu_control, result, zero, overflow);
                pass_count = pass_count + 1;
            end else begin
                $display("FAIL: %s - A=%h, B=%h, Control=%b", test_name, a, b, alu_control);
                $display("      Expected: Result=%h, Zero=%b, Overflow=%b", expected_result, expected_zero, expected_overflow);
                $display("      Got:      Result=%h, Zero=%b, Overflow=%b", result, zero, overflow);
                fail_count = fail_count + 1;
            end
        end
    endtask

    initial begin
        $dumpfile("alu_16bit_tb.vcd");
        $dumpvars(0, alu_16bit_tb);
        
        $display("Starting ALU 16-bit Test");
        $display("========================");
        
        test_count = 0;
        pass_count = 0;
        fail_count = 0;

        #10;

        // Test Case 1: ADD - Positive numbers
        a = 16'h1234;
        b = 16'h5678;
        alu_control = 4'b0000;
        #10;
        check_result(16'h68AC, 1'b0, 1'b0, "ADD positive numbers");

        // Test Case 2: ADD - Zero result
        a = 16'h0000;
        b = 16'h0000;
        alu_control = 4'b0000;
        #10;
        check_result(16'h0000, 1'b1, 1'b0, "ADD zero result");

        // Test Case 3: ADD - Overflow (positive + positive = negative)
        a = 16'h7FFF;
        b = 16'h0001;
        alu_control = 4'b0000;
        #10;
        check_result(16'h8000, 1'b0, 1'b1, "ADD overflow positive");

        // Test Case 4: SUB - Positive result
        a = 16'h5678;
        b = 16'h1234;
        alu_control = 4'b0001;
        #10;
        check_result(16'h4444, 1'b0, 1'b0, "SUB positive result");

        // Test Case 5: SUB - Zero result
        a = 16'hABCD;
        b = 16'hABCD;
        alu_control = 4'b0001;
        #10;
        check_result(16'h0000, 1'b1, 1'b0, "SUB zero result");

        // Test Case 6: SUB - Overflow (negative - positive = positive)
        a = 16'h8000;
        b = 16'h0001;
        alu_control = 4'b0001;
        #10;
        check_result(16'h7FFF, 1'b0, 1'b1, "SUB overflow");

        // Test Case 7: AND - All bits set
        a = 16'hFFFF;
        b = 16'h5555;
        alu_control = 4'b0010;
        #10;
        check_result(16'h5555, 1'b0, 1'b0, "AND operation");

        // Test Case 8: OR - Mixed bits
        a = 16'h5555;
        b = 16'hAAAA;
        alu_control = 4'b0011;
        #10;
        check_result(16'hFFFF, 1'b0, 1'b0, "OR operation");

        // Test Case 9: XOR - Same values (zero result)
        a = 16'h1234;
        b = 16'h1234;
        alu_control = 4'b0100;
        #10;
        check_result(16'h0000, 1'b1, 1'b0, "XOR zero result");

        // Test Case 10: XOR - Different values
        a = 16'hFFFF;
        b = 16'h5555;
        alu_control = 4'b0100;
        #10;
        check_result(16'hAAAA, 1'b0, 1'b0, "XOR different values");

        // Test Case 11: SLT - A < B (signed)
        a = 16'hFFFF; // -1 in signed
        b = 16'h0001; // +1 in signed
        alu_control = 4'b0101;
        #10;
        check_result(16'h0001, 1'b0, 1'b0, "SLT A < B (signed)");

        // Test Case 12: SLT - A >= B (signed)
        a = 16'h0002; // +2 in signed
        b = 16'h0001; // +1 in signed
        alu_control = 4'b0101;
        #10;
        check_result(16'h0000, 1'b1, 1'b0, "SLT A >= B (signed)");

        // Test Case 13: Boundary case - Maximum positive
        a = 16'h7FFF;
        b = 16'h0000;
        alu_control = 4'b0000;
        #10;
        check_result(16'h7FFF, 1'b0, 1'b0, "ADD max positive + zero");

        // Test Case 14: Boundary case - Maximum negative
        a = 16'h8000;
        b = 16'h0000;
        alu_control = 4'b0000;
        #10;
        check_result(16'h8000, 1'b0, 1'b0, "ADD max negative + zero");

        #10;

        $display("\n========================");
        $display("Test Summary:");
        $display("Total Tests: %0d", test_count);
        $display("Passed:      %0d", pass_count);
        $display("Failed:      %0d", fail_count);
        
        if (fail_count == 0) begin
            $display("ALL TESTS PASSED!");
        end else begin
            $display("SOME TESTS FAILED!");
        end
        $display("========================");

        $finish;
    end

endmodule

alu_16bit_tb.vcd
$date
	Thu Aug 14 17:07:51 2025
$end
$version
	Icarus Verilog
$end
$timescale
	1s
$end
$scope module alu_16bit_tb $end
$var wire 1 ! zero $end
$var wire 16 " result [15:0] $end
$var wire 1 # overflow $end
$var reg 16 $ a [15:0] $end
$var reg 4 % alu_control [3:0] $end
$var reg 16 & b [15:0] $end
$var integer 32 ' fail_count [31:0] $end
$var integer 32 ( pass_count [31:0] $end
$var integer 32 ) test_count [31:0] $end
$scope module dut $end
$var wire 16 * a [15:0] $end
$var wire 4 + alu_control [3:0] $end
$var wire 16 , b [15:0] $end
$var wire 1 # overflow $end
$var wire 16 - result [15:0] $end
$var wire 1 ! zero $end
$var reg 1 . alu_overflow $end
$var reg 16 / alu_result [15:0] $end
$upscope $end
$scope task check_result $end
$var reg 1 0 expected_overflow $end
$var reg 16 1 expected_result [15:0] $end
$var reg 1 2 expected_zero $end
$var reg 256 3 test_name [255:0] $end
$upscope $end
$upscope $end
$enddefinitions $end
#0
$dumpvars
bx 3
x2
bx 1
x0
bx /
x.
bx -
bx ,
bx +
bx *
b0 )
b0 (
b0 '
bx &
bx %
bx $
x#
bx "
x!
$end
#10
0!
b110100010101100 "
b110100010101100 -
b110100010101100 /
0#
0.
b0 %
b0 +
b101011001111000 &
b101011001111000 ,
b1001000110100 $
b1001000110100 *
#20
1!
b0 "
b0 -
b0 /
b0 &
b0 ,
b0 $
b0 *
b1 (
b1 )
b100000101000100010001000010000001110000011011110111001101101001011101000110100101110110011001010010000001101110011101010110110101100010011001010111001001110011 3
00
02
b110100010101100 1
#30
1#
1.
0!
b1000000000000000 "
b1000000000000000 -
b1000000000000000 /
b1 &
b1 ,
b111111111111111 $
b111111111111111 *
b10 (
b10 )
b10000010100010001000100001000000111101001100101011100100110111100100000011100100110010101110011011101010110110001110100 3
12
b0 1
#40
b100010001000100 "
b100010001000100 -
b100010001000100 /
0#
0.
b1 %
b1 +
b1001000110100 &
b1001000110100 ,
b101011001111000 $
b101011001111000 *
b11 (
b11 )
b10000010100010001000100001000000110111101110110011001010111001001100110011011000110111101110111001000000111000001101111011100110110100101110100011010010111011001100101 3
10
02
b1000000000000000 1
#50
1!
b0 "
b0 -
b0 /
b1010101111001101 &
b1010101111001101 ,
b1010101111001101 $
b1010101111001101 *
b100 (
b100 )
b1010011010101010100001000100000011100000110111101110011011010010111010001101001011101100110010100100000011100100110010101110011011101010110110001110100 3
00
b100010001000100 1
#60
1#
1.
0!
b111111111111111 "
b111111111111111 -
b111111111111111 /
b1 &
b1 ,
b1000000000000000 $
b1000000000000000 *
b101 (
b101 )
b10100110101010101000010001000000111101001100101011100100110111100100000011100100110010101110011011101010110110001110100 3
12
b0 1
#70
b101010101010101 "
b101010101010101 -
b101010101010101 /
0#
0.
b10 %
b10 +
b101010101010101 &
b101010101010101 ,
b1111111111111111 $
b1111111111111111 *
b110 (
b110 )
b10100110101010101000010001000000110111101110110011001010111001001100110011011000110111101110111 3
10
02
b111111111111111 1
#80
b1111111111111111 "
b1111111111111111 -
b1111111111111111 /
b11 %
b11 +
b1010101010101010 &
b1010101010101010 ,
b101010101010101 $
b101010101010101 *
b111 (
b111 )
b1000001010011100100010000100000011011110111000001100101011100100110000101110100011010010110111101101110 3
00
b101010101010101 1
#90
1!
b0 "
b0 -
b0 /
b100 %
b100 +
b1001000110100 &
b1001000110100 ,
b1001000110100 $
b1001000110100 *
b1000 (
b1000 )
b10011110101001000100000011011110111000001100101011100100110000101110100011010010110111101101110 3
b1111111111111111 1
#100
0!
b1010101010101010 "
b1010101010101010 -
b1010101010101010 /
b101010101010101 &
b101010101010101 ,
b1111111111111111 $
b1111111111111111 *
b1001 (
b1001 )
b10110000100111101010010001000000111101001100101011100100110111100100000011100100110010101110011011101010110110001110100 3
12
b0 1
#110
b1 "
b1 -
b1 /
b101 %
b101 +
b1 &
b1 ,
b1010 (
b1010 )
b101100001001111010100100010000001100100011010010110011001100110011001010111001001100101011011100111010000100000011101100110000101101100011101010110010101110011 3
02
b1010101010101010 1
#120
1!
b0 "
b0 -
b0 /
b10 $
b10 *
b1011 (
b1011 )
b10100110100110001010100001000000100000100100000001111000010000001000010001000000010100001110011011010010110011101101110011001010110010000101001 3
b1 1
#130
0!
b111111111111111 "
b111111111111111 -
b111111111111111 /
b0 %
b0 +
b0 &
b0 ,
b111111111111111 $
b111111111111111 *
b1100 (
b1100 )
b1010011010011000101010000100000010000010010000000111110001111010010000001000010001000000010100001110011011010010110011101101110011001010110010000101001 3
12
b0 1
#140
b1000000000000000 "
b1000000000000000 -
b1000000000000000 /
b1000000000000000 $
b1000000000000000 *
b1101 (
b1101 )
b100000101000100010001000010000001101101011000010111100000100000011100000110111101110011011010010111010001101001011101100110010100100000001010110010000001111010011001010111001001101111 3
02
b111111111111111 1
#150
b1110 (
b1110 )
b100000101000100010001000010000001101101011000010111100000100000011011100110010101100111011000010111010001101001011101100110010100100000001010110010000001111010011001010111001001101111 3
b1000000000000000 1
